{
  "HospitalityDescriptiveInfoRQ" : {
    "version" : 1,
    "timeStamp" : "2020-01-31T10:41:07.146-05:00",
    "PayloadStdAttributes" : {
      "value" : null,
      "echoToken" : "Example String Value",
      "timeStamp" : "2011-01-24T09:45:00-06:00",
      "target" : "Test",
      "targetName" : "Example String Value",
      "version" : 12,
      "transactionIdentifier" : "Example String Value",
      "sequenceNmbr" : "Example String Value",
      "transactionStatusCode" : "Start",
      "correlationID" : "Example String Value",
      "primaryLangID" : "en",
      "altLangID" : "es",
      "retransmissionIndicatorInd" : true
    },
    "POS" : {
      "@type" : "POS",
      "Source" : [ {
        "@type" : "Source",
        "agentSine" : "Example String Value",
        "pseudoCityCode" : "Example String Value",
        "iSOCountry" : "IR",
        "iSOCurrency" : "USD",
        "agentDutyCode" : "Example String Value",
        "airlineVendorID" : "B6",
        "airportCode" : "IAD",
        "firstDepartPoint" : "Example String Value",
        "eRSP_UserID" : "Example String Value",
        "terminalID" : "Example String Value",
        "RequestorID" : {
          "@type" : "RequestorID",
          "Identifier" : {
            "value" : "guid12345",
            "url" : "http://www.w3.org/2001/XMLSchema",
            "system" : "sysABC3344",
            "organization" : "Acme"
          }
        },
        "Position" : {
          "value" : null,
          "latitude" : "Example String Value",
          "longitude" : "Example String Value",
          "altitude" : "Example String Value",
          "altitudeUnitOfMeasure_Enum" : "Miles",
          "mapURL" : "http://www.OpenTravel.org/ns/OTA2/Common_v01_00",
          "formatURL" : "http://www.w3.org/2001/XMLSchema"
        },
        "BookingChannel" : {
          "@type" : "BookingChannel",
          "primaryInd" : true,
          "CompanyName" : {
            "value" : "Travel Adventure Partners Incorporated",
            "division" : "Travel Division",
            "department" : "Adventure department",
            "shortName" : "Adventure Inc",
            "code" : "AI",
            "codeContext" : "Example String Value",
            "description" : "Example String Value",
            "quantity" : 1234,
            "listURI" : "Example String Value"
          },
          "Type" : {
            "value" : "Agent"
          }
        }
      } ]
    },
    "ProcessingInfo" : {
      "value" : null,
      "displayCurrency" : "USD",
      "maxResponses" : 1234,
      "summaryResultsInd" : true
    },
    "HotelDescriptiveRequestInfo" : {
      "@type" : "HotelDescriptiveRequestInfo",
      "languageRequested" : "???",
      "BasicPropertyInfo" : [ {
        "@type" : "BasicPropertyInfo",
        "code" : "WASJW",
        "name" : "JW Marriott Washington DC",
        "chainCode" : "MC",
        "brandCode" : "FS",
        "cityCode" : "WAS"
      } ],
      "HotelRequestInfo" : {
        "@type" : "HotelRequestInfo",
        "hotelStatus" : "Example String Value",
        "sendDataInd" : true,
        "HotelStatusCode" : {
          "value" : "Closed"
        }
      },
      "FacilityRequestInfo" : {
        "value" : null,
        "sendMeetingRoomsInd" : true,
        "sendGuestRoomsInd" : true,
        "sendRestaurantsInd" : true
      },
      "PolicyRequestInfo" : {
        "value" : null,
        "sendPoliciesInd" : true
      },
      "AreaRequestInfo" : {
        "value" : null,
        "sendRefPointsInd" : true,
        "sendAttractionsInd" : true,
        "sendRecreationsInd" : true
      },
      "AffiliationRequestInfo" : {
        "value" : null,
        "sendDistribSystemsInd" : true,
        "sendBrandInd" : true,
        "sendLoyalProgramsInd" : true,
        "sendAwardsInd" : true
      }
    }
  }
}