{
  "PracticeFacilities" : {
    "OperationSchedule" : [ {
      "daysOfWeek" : [ "Monday", "Tuesday", "Wednesday" ],
      "additionalOperationInfoCode" : "2",
      "frequency" : "Example String Value",
      "text" : "Example String Value",
      "name" : "Example String Value",
      "DateTimeSpanWindows" : {
        "@type" : "DateTimeSpanWindows",
        "TimeSpan" : {
          "value" : null,
          "start" : "2016-08-22T19:32:52Z",
          "end" : "2016-08-28T04:32:52Z"
        }
      }
    } ],
    "DrivingRange" : [ {
      "@type" : "DrivingRange",
      "turfType" : "Grass",
      "distance" : "500 ft",
      "numberOfStations" : 10,
      "drivingRangeType" : "Covered",
      "nightLightingInd" : true
    } ],
    "FeeStructure" : {
      "value" : null,
      "minRate" : 100.0000,
      "maxRate" : 100.0000,
      "fixedRate" : 100.0000,
      "rateTimeUnit" : "Day",
      "currencyCode" : "USD"
    },
    "PracticeFacilityFeatures" : [ {
      "value" : "PuttingGreen"
    }, {
      "value" : "PuttingGreen"
    } ]
  }
}